{"stats":{"minecraft:picked_up":{"minecraft:dirt":1},"minecraft:used":{"minecraft:dirt":1},"minecraft:mined":{"minecraft:grass":3,"minecraft:dirt":1,"minecraft:jungle_leaves":3,"minecraft:oak_leaves":4},"minecraft:killed_by":{"minecraft:panda":1,"pangea_ultima:ostrich":1},"minecraft:custom":{"minecraft:time_since_rest":485,"minecraft:crouch_one_cm":11,"minecraft:play_time":14507,"minecraft:sprint_one_cm":871,"minecraft:walk_one_cm":31160,"minecraft:damage_taken":770,"minecraft:deaths":3,"minecraft:sneak_time":1074,"minecraft:walk_under_water_one_cm":47335,"minecraft:jump":510,"minecraft:damage_dealt":56,"minecraft:leave_game":1,"minecraft:time_since_death":463,"minecraft:walk_on_water_one_cm":10012,"minecraft:total_world_time":17123,"minecraft:climb_one_cm":17824,"minecraft:fall_one_cm":18225,"minecraft:fly_one_cm":95902}},"DataVersion":3120}